[
  {
    "thema": "Milieuzone",
    "categorie": "M1",
    "prioriteit": 0,
    "datum": "2023-12-13",
    "titel": "Uw aanvraag ontheffing milieuzone Brom- en snorfietsen",
    "omschrijving": "U moet uw aanvraag voor ontheffing milieuzone Brom- en snorfietsen nog betalen",
    "url": "https://ontheffingen-acc.amsterdam.nl/publiek/aanvraag/56B31535-1404-4AC0-8658-CD77C32C12EE",
    "urlNaam": "Betaal direct"
  },
  {
    "thema": "Milieuzone",
    "categorie": "F3",
    "prioriteit": 0,
    "datum": "2020-12-21",
    "titel": "Uw aanvraag ontheffing milieuzone Vracht",
    "omschrijving": "Uw aanvraag voor ontheffing milieuzone Vracht is toegekend",
    "url": "https://ontheffingen-acc.amsterdam.nl/publiek/aanvraag/2a5d9103-42bb-4a88-9bf9-5cd58580e209",
    "urlNaam": "Meer informatie"
  },
  {
    "thema": "Milieuzone",
    "categorie": "F3",
    "prioriteit": 0,
    "datum": "2019-12-13",
    "titel": "Uw aanvraag ontheffing milieuzone Brom- en snorfietsen",
    "omschrijving": "Uw aanvraag voor ontheffing milieuzone Brom- en snorfietsen is toegekend",
    "url": "https://ontheffingen-acc.amsterdam.nl/publiek/aanvraag/7B46A24E-BC21-44F9-ADB8-B85A75FAFB90",
    "urlNaam": "Meer informatie"
  },
  {
    "thema": "Milieuzone",
    "categorie": "F2",
    "prioriteit": 50,
    "datum": "2023-10-12",
    "titel": "Ontheffing milieuzone",
    "omschrijving": "",
    "url": "https://ontheffingen-acc.amsterdam.nl/publiek/aanvragen",
    "urlNaam": "Milieuzone"
  },
  {
    "thema": "Milieuzone",
    "categorie": "M1",
    "prioriteit": 0,
    "datum": "2019-12-13",
    "titel": "Uw aanvraag ontheffing milieuzone Brom- en snorfietsen",
    "omschrijving": "U moet uw aanvraag voor ontheffing milieuzone Brom- en snorfietsen nog betalen",
    "url": "https://ontheffingen-acc.amsterdam.nl/publiek/aanvraag/88D12139-6BFF-45BF-9FA5-4BFCC01F284F",
    "urlNaam": "Betaal direct"
  },
  {
    "thema": "Milieuzone",
    "categorie": "F3",
    "prioriteit": 0,
    "datum": "2019-12-13",
    "titel": "Uw aanvraag ontheffing milieuzone Brom- en snorfietsen",
    "omschrijving": "Uw aanvraag voor ontheffing milieuzone Brom- en snorfietsen is toegekend",
    "url": "https://ontheffingen-acc.amsterdam.nl/publiek/aanvraag/3A36D276-244D-4B12-8A43-97573502728E",
    "urlNaam": "Meer informatie"
  },
  {
    "thema": "Overtredingen",
    "categorie": "F2",
    "prioriteit": 50,
    "datum": "2023-10-12",
    "titel": "Overtredingen",
    "omschrijving": "",
    "url": "https://ontheffingen-acc.amsterdam.nl/publiek/aanvragen",
    "urlNaam": "Overtredingen"
  },
  {
    "thema": "Milieuzone",
    "categorie": "F3",
    "prioriteit": 0,
    "datum": "2019-12-13",
    "titel": "Uw aanvraag ontheffing milieuzone Brom- en snorfietsen",
    "omschrijving": "Uw aanvraag voor ontheffing milieuzone Brom- en snorfietsen is afgewezen",
    "url": "https://ontheffingen-acc.amsterdam.nl/publiek/aanvraag/5A158FD9-B07D-4A4C-B780-8359A9A14906",
    "urlNaam": "Meer informatie"
  },
  {
    "thema": "Overtredingen",
    "categorie": "F3",
    "prioriteit": 0,
    "datum": "2023-12-14",
    "titel": "U bent een milieuzone ingereden",
    "omschrijving": "U bent een milieuzone ingereden, betaal op tijd.",
    "url": "https://ontheffingen-acc.amsterdam.nl/publiek/aanvraag/2A3B4C05-700C-4C1E-A399-4E171F5B5420",
    "urlNaam": "Meer informatie"
  },
  {
    "thema": "Milieuzone",
    "categorie": "M1",
    "prioriteit": 0,
    "datum": "2021-10-18",
    "titel": "Uw aanvraag ontheffing milieuzone Vracht",
    "omschrijving": "Uw moet uw aanvraag voor ontheffing milieuzone Vracht nog betalen",
    "url": "https://ontheffingen-acc.amsterdam.nl/publiek/aanvraag/e9d0d30b-2de4-4c7a-9340-4e784d51f1d6",
    "urlNaam": "Betaal direct"
  }
]
